patent_mcp/__init__.py
patent_mcp/client.py
patent_mcp/database.py
patent_mcp/scoring.py
patent_mcp/server.py
mseep_mseep_patent_mcp-0.1.0.dist-info/METADATA
mseep_mseep_patent_mcp-0.1.0.dist-info/WHEEL
mseep_mseep_patent_mcp-0.1.0.dist-info/top_level.txt
mseep_mseep_patent_mcp-0.1.0.dist-info/RECORD
