Metadata-Version: 2.4
Name: mseep_mseep-patent_mcp
Version: 0.1.0
Summary: Package published under mseep brand
Author-email: mseep <support@skydeck.ai>
Requires-Python: >=3.11
Dynamic: requires-python
